{
	"@type":"Process",
	"Name":"}Plans_CopyPlan",
	"HasSecurityAccess":false,
	"Code@Code.link":"}Plans_CopyPlan.ti",
	"UIData":"_ParameterConstraints=e30=\f",
	"DataSource":
	{
		"Type":"None"
	},
	"Parameters":
	[
		{
			"Name":"pPlan",
			"Prompt":"",
			"Value":"",
			"Type":"String"
		},
		{
			"Name":"pNewPlan",
			"Prompt":"",
			"Value":"",
			"Type":"String"
		},
		{
			"Name":"pReplace",
			"Prompt":"'Y' to replace existing plan ",
			"Value":"N",
			"Type":"String"
		},
		{
			"Name":"pPrefix",
			"Prompt":"",
			"Value":"}Plans",
			"Type":"String"
		}
	],
	"Variables":[]
}